ale_uy/__init__.py
ale_uy/dl.py
ale_uy/eda.py
ale_uy/ml.py
ale_uy/ts.py
ale_uy-1.5.0.dist-info/LICENSE
ale_uy-1.5.0.dist-info/METADATA
ale_uy-1.5.0.dist-info/WHEEL
ale_uy-1.5.0.dist-info/top_level.txt
ale_uy-1.5.0.dist-info/RECORD
