Metadata-Version: 2.1
Name: ale-uy
Version: 1.5.0
Summary: Tool to perform data cleaning, modeling and visualization in a simple way.
Home-page: https://github.com/ale-uy/DataScience
Author: ale-uy
License-File: LICENSE
Requires-Dist: ale-uy
Requires-Dist: catboost ==1.2.1.1
Requires-Dist: cmdstanpy ==1.1.0
Requires-Dist: colorama ==0.4.6
Requires-Dist: contourpy ==1.1.1
Requires-Dist: convertdate ==2.4.0
Requires-Dist: cycler ==0.11.0
Requires-Dist: ephem ==4.1.4
Requires-Dist: fonttools ==4.42.1
Requires-Dist: graphviz ==0.20.1
Requires-Dist: holidays ==0.33
Requires-Dist: imbalanced-learn ==0.11.0
Requires-Dist: importlib-resources ==6.1.0
Requires-Dist: joblib ==1.3.2
Requires-Dist: kiwisolver ==1.4.5
Requires-Dist: lightgbm ==4.1.0
Requires-Dist: LunarCalendar ==0.0.9
Requires-Dist: matplotlib ==3.8.0
Requires-Dist: numpy ==1.26.0
Requires-Dist: packaging ==23.1
Requires-Dist: pandas ==2.1.0
Requires-Dist: patsy ==0.5.3
Requires-Dist: Pillow ==10.0.1
Requires-Dist: plotly ==5.17.0
Requires-Dist: prophet ==1.1.4
Requires-Dist: PyMeeus ==0.5.12
Requires-Dist: pyparsing ==3.1.1
Requires-Dist: python-dateutil ==2.8.2
Requires-Dist: pytz ==2023.3.post1
Requires-Dist: scikit-learn ==1.3.0
Requires-Dist: scipy ==1.11.2
Requires-Dist: seaborn ==0.12.2
Requires-Dist: six ==1.16.0
Requires-Dist: statsmodels ==0.14.0
Requires-Dist: tenacity ==8.2.3
Requires-Dist: threadpoolctl ==3.2.0
Requires-Dist: tqdm ==4.66.1
Requires-Dist: tzdata ==2023.3
Requires-Dist: xgboost ==2.0.0
Requires-Dist: notebook ==7.0.4
Requires-Dist: ipywidgets ==8.1.1
Requires-Dist: tensorflow ==2.10.0
Requires-Dist: keras-tuner ==1.4.4
